README.txt
setup.py
pyschedules/__init__.py
pyschedules/retrieve.py
pyschedules/xml_callbacks.py
pyschedules.egg-info/PKG-INFO
pyschedules.egg-info/SOURCES.txt
pyschedules.egg-info/dependency_links.txt
pyschedules.egg-info/entry_points.txt
pyschedules.egg-info/requires.txt
pyschedules.egg-info/top_level.txt
pyschedules.egg-info/zip-safe
pyschedules/examples/__init__.py
pyschedules/examples/read.py
pyschedules/interfaces/__init__.py
pyschedules/interfaces/ientity_trigger.py
pyschedules/interfaces/iprogress_trigger.py
scripts/qam.py